{
  "version": "0.2.0-salesforce-lwr",
  "generatedAt": "2026-07-08T22:45:39.482Z",
  "provider": "spen",
  "attempts": [
    {
      "id": "salesforce-lwr-counts",
      "ok": true,
      "liveCount": 8,
      "plannedCount": 2,
      "restoredCount": 52
    },
    {
      "id": "salesforce-lwr-pages",
      "ok": true,
      "liveRows": 8,
      "plannedRows": 2,
      "restoredRows": 52
    },
    {
      "id": "postcodes-io-geocoding",
      "ok": true,
      "lookups": 61,
      "mappedRows": 60
    }
  ],
  "result": {
    "officialLiveCount": 8,
    "rawRows": 62,
    "validRows": 60,
    "uniqueIncidents": 60,
    "categories": {
      "current": 8,
      "planned": 1,
      "restored": 51
    }
  }
}
